{
  "gizmos-infos": {
    "is2D": true,
    "is3DIcon": false,
    "iconSize": 2,
    "gridVisible": true,
    "gridColor": [
      166,
      166,
      166,
      255
    ],
    "transformToolName": "position",
    "pivot": "center",
    "coordinate": "local",
    "toolsVisibility3d": true
  },
  "__version__": "1.0.2",
  "builder": {
    "taskOptionsMap": {},
    "__version__": "1.3.9"
  },
  "snap-configs": {
    "position": {
      "x": 1,
      "y": 1,
      "z": 1
    },
    "rotation": 1,
    "scale": 1,
    "isPositionSnapEnabled": false,
    "isRotationSnapEnabled": false,
    "isScaleSnapEnabled": false
  },
  "rect-snap-configs": {
    "enableSnapping": true,
    "snapThreshold": 4
  },
  "float-window": {
    "position": {
      "cc": {
        "Camera": {
          "dock": false,
          "top": null,
          "bottom": 10,
          "left": null,
          "right": 10
        }
      }
    }
  },
  "camera-infos": {
    "b84b8381-b0d5-4bde-a44a-b846cc861561": {
      "position": {
        "x": 750,
        "y": 1500,
        "z": 5000
      },
      "rotation": {
        "x": 0,
        "y": 0,
        "z": 0,
        "w": 1
      },
      "viewCenter": {
        "x": 0,
        "y": 0,
        "z": 0
      },
      "contentRect": {
        "x": 726,
        "y": 1441,
        "width": 171.13220338983052,
        "height": 420.70000000000005
      },
      "scale": 3.565254237288136
    },
    "ee4dd54d-d571-48fd-b7b2-188e2cc5b1f6": {
      "position": {
        "x": 750,
        "y": 1500,
        "z": 5000
      },
      "rotation": {
        "x": 0,
        "y": 0,
        "z": 0,
        "w": 1
      },
      "viewCenter": {
        "x": 0,
        "y": 0,
        "z": 0
      },
      "contentRect": {
        "x": 726,
        "y": 1441,
        "width": 171.13220338983052,
        "height": 420.70000000000005
      },
      "scale": 3.565254237288136
    },
    "2d6df1b9-3994-4ef9-afa0-a28e99598b38": {
      "position": {
        "x": 750,
        "y": 1500,
        "z": 5000
      },
      "rotation": {
        "x": 0,
        "y": 0,
        "z": 0,
        "w": 1
      },
      "viewCenter": {
        "x": 0,
        "y": 0,
        "z": 0
      },
      "contentRect": {
        "x": 726,
        "y": 1441,
        "width": 171.13220338983052,
        "height": 420.70000000000005
      },
      "scale": 3.565254237288136
    },
    "8c8615ca-7b4e-43c1-b2cc-f72964472297": {
      "position": {
        "x": 750,
        "y": 1500,
        "z": 5000
      },
      "rotation": {
        "x": 0,
        "y": 0,
        "z": 0,
        "w": 1
      },
      "viewCenter": {
        "x": 0,
        "y": 0,
        "z": 0
      },
      "contentRect": {
        "x": 707.9272640836701,
        "y": 1478.9636320418351,
        "width": 744,
        "height": 601
      },
      "scale": 3.565254237288136
    },
    "37571cfd-8ab2-41d5-89a4-919bc2257e6f": {
      "position": {
        "x": 750,
        "y": 1500,
        "z": 5000
      },
      "rotation": {
        "x": 0,
        "y": 0,
        "z": 0,
        "w": 1
      },
      "viewCenter": {
        "x": 0,
        "y": 0,
        "z": 0
      },
      "contentRect": {
        "x": 700,
        "y": 1450,
        "width": 420.70000000000005,
        "height": 420.70000000000005
      },
      "scale": 4.207000000000001
    },
    "ccb39f74-662f-429e-8cda-db02366bf329": {
      "position": {
        "x": 516.2833333333334,
        "y": 751.9833333333333,
        "z": 5000
      },
      "rotation": {
        "x": 0,
        "y": 0,
        "z": 0,
        "w": 1
      },
      "viewCenter": {
        "x": 0,
        "y": 0,
        "z": 0
      },
      "contentRect": {
        "x": 228.99999999999994,
        "y": 0,
        "width": 744,
        "height": 572
      },
      "scale": 0.7
    },
    "54ce050a-2514-4bb4-b5ed-5e1744cf83b8": {
      "position": {
        "x": 350.74666666666667,
        "y": 703.4633333333334,
        "z": 5000
      },
      "rotation": {
        "x": 0,
        "y": 0,
        "z": 0,
        "w": 1
      },
      "viewCenter": {
        "x": 0,
        "y": 0,
        "z": 0
      },
      "contentRect": {
        "x": 0,
        "y": 0,
        "width": 286,
        "height": 572
      },
      "scale": 0.7
    },
    "2034b8c5-1146-458f-8ba5-25be772802d6": {
      "position": {
        "x": 499.9999999999999,
        "y": 949.9999999999998,
        "z": 5000
      },
      "rotation": {
        "x": 0,
        "y": 0,
        "z": 0,
        "w": 1
      },
      "viewCenter": {
        "x": 0,
        "y": 0,
        "z": 0
      },
      "contentRect": {
        "x": -940,
        "y": -490,
        "width": 420.7000000000001,
        "height": 420.70000000000005
      },
      "scale": 0.14607638888888894
    },
    "13cc6695-c655-4495-9675-6a468b3eaa56": {
      "position": {
        "x": 350.74666666666667,
        "y": 703.4633333333334,
        "z": 5000
      },
      "rotation": {
        "x": 0,
        "y": 0,
        "z": 0,
        "w": 1
      },
      "viewCenter": {
        "x": 0,
        "y": 0,
        "z": 0
      },
      "contentRect": {
        "x": 0,
        "y": 0,
        "width": 286,
        "height": 572
      },
      "scale": 0.7
    },
    "075ef6fe-19e9-48a4-9888-94c9a96669d3": {
      "position": {
        "x": 749.9999999999998,
        "y": 1499.9999999999995,
        "z": 5000
      },
      "rotation": {
        "x": 0,
        "y": 0,
        "z": 0,
        "w": 1
      },
      "viewCenter": {
        "x": 0,
        "y": 0,
        "z": 0
      },
      "contentRect": {
        "x": 0,
        "y": 0,
        "width": 210.35000000000005,
        "height": 420.70000000000005
      },
      "scale": 0.14023333333333338
    },
    "fc2e5167-dc70-498f-9c79-e6dcb2f72269": {
      "position": {
        "x": 749.5633333333334,
        "y": 1063.77,
        "z": 5000
      },
      "rotation": {
        "x": 0,
        "y": 0,
        "z": 0,
        "w": 1
      },
      "viewCenter": {
        "x": 0,
        "y": 0,
        "z": 0
      },
      "contentRect": {
        "x": 500.00000000000006,
        "y": 0,
        "width": 1500,
        "height": 1000
      },
      "scale": 0.7
    },
    "4a6628bc-5169-4414-9121-557593015fb1": {
      "position": {
        "x": 427.46333333333337,
        "y": 856.5366666666667,
        "z": 5000
      },
      "rotation": {
        "x": 0,
        "y": 0,
        "z": 0,
        "w": 1
      },
      "viewCenter": {
        "x": 0,
        "y": 0,
        "z": 0
      },
      "contentRect": {
        "x": 0,
        "y": 0,
        "width": 300,
        "height": 600
      },
      "scale": 0.7
    },
    "ffda4a59-2bbf-4520-8804-1ee2f0b6a7a8": {
      "position": {
        "x": 400.4183333333333,
        "y": 802.5816666666667,
        "z": 5000
      },
      "rotation": {
        "x": 0,
        "y": 0,
        "z": 0,
        "w": 1
      },
      "viewCenter": {
        "x": 0,
        "y": 0,
        "z": 0
      },
      "contentRect": {
        "x": 0,
        "y": 0,
        "width": 300,
        "height": 600
      },
      "scale": 0.7
    },
    "30610f8e-e61d-4828-8baa-b7cd2a3dcda2": {
      "position": {
        "x": 750,
        "y": 1500,
        "z": 5000
      },
      "rotation": {
        "x": 0,
        "y": 0,
        "z": 0,
        "w": 1
      },
      "viewCenter": {
        "x": 0,
        "y": 0,
        "z": 0
      },
      "contentRect": {
        "x": 0,
        "y": 0,
        "width": 300,
        "height": 600
      },
      "scale": 0.7
    },
    "d69e9f1c-5a10-4af2-b2e1-f1791b9ce753": {
      "position": {
        "x": 750,
        "y": 1500,
        "z": 5000
      },
      "rotation": {
        "x": 0,
        "y": 0,
        "z": 0,
        "w": 1
      },
      "viewCenter": {
        "x": 0,
        "y": 0,
        "z": 0
      },
      "contentRect": {
        "x": 700,
        "y": 1450,
        "width": 420.70000000000005,
        "height": 420.70000000000005
      },
      "scale": 4.207000000000001
    },
    "d27bc379-4a6b-4e9b-beb2-4bf70f9b1127": {
      "position": {
        "x": 750,
        "y": 1500,
        "z": 5000
      },
      "rotation": {
        "x": 0,
        "y": 0,
        "z": 0,
        "w": 1
      },
      "viewCenter": {
        "x": 0,
        "y": 0,
        "z": 0
      },
      "contentRect": {
        "x": 700,
        "y": 1450,
        "width": 420.70000000000005,
        "height": 420.70000000000005
      },
      "scale": 4.207000000000001
    },
    "6be07cc3-fad6-4fd7-8f13-cc76de2fcc01": {
      "position": {
        "x": 750,
        "y": 1500,
        "z": 5000
      },
      "rotation": {
        "x": 0,
        "y": 0,
        "z": 0,
        "w": 1
      },
      "viewCenter": {
        "x": 0,
        "y": 0,
        "z": 0
      },
      "contentRect": {
        "x": 229.25,
        "y": 0,
        "width": 745,
        "height": 573
      },
      "scale": 0.7000000000000001
    },
    "82aa19b1-0fe6-44f9-b6b2-0179d5eec652": {
      "position": {
        "x": 750,
        "y": 1500,
        "z": 5000
      },
      "rotation": {
        "x": 0,
        "y": 0,
        "z": 0,
        "w": 1
      },
      "viewCenter": {
        "x": 0,
        "y": 0,
        "z": 0
      },
      "contentRect": {
        "x": 0,
        "y": 0,
        "width": 300,
        "height": 600
      },
      "scale": 0.7
    },
    "3f5f3bd5-c82f-4d47-ac9f-7424735b4f41": {
      "position": {
        "x": 750,
        "y": 1500,
        "z": 5000
      },
      "rotation": {
        "x": 0,
        "y": 0,
        "z": 0,
        "w": 1
      },
      "viewCenter": {
        "x": 0,
        "y": 0,
        "z": 0
      },
      "contentRect": {
        "x": 0,
        "y": 0,
        "width": 300,
        "height": 600
      },
      "scale": 0.7
    },
    "9dbe4a48-eef1-4ad7-8922-37dc4e113efc": {
      "position": {
        "x": 750,
        "y": 1500,
        "z": 5000
      },
      "rotation": {
        "x": 0,
        "y": 0,
        "z": 0,
        "w": 1
      },
      "viewCenter": {
        "x": 0,
        "y": 0,
        "z": 0
      },
      "contentRect": {
        "x": 0,
        "y": 0,
        "width": 300,
        "height": 600
      },
      "scale": 0.7
    },
    "1c15e859-8b57-4952-b5e6-4b24288d4c2d": {
      "position": {
        "x": 750,
        "y": 1500,
        "z": 5000
      },
      "rotation": {
        "x": 0,
        "y": 0,
        "z": 0,
        "w": 1
      },
      "viewCenter": {
        "x": 0,
        "y": 0,
        "z": 0
      },
      "contentRect": {
        "x": 0,
        "y": 0,
        "width": 300,
        "height": 600
      },
      "scale": 0.7
    },
    "0abd7c88-5b0f-4b95-a22d-f723f2d30f98": {
      "position": {
        "x": 750,
        "y": 1500,
        "z": 5000
      },
      "rotation": {
        "x": 0,
        "y": 0,
        "z": 0,
        "w": 1
      },
      "viewCenter": {
        "x": 0,
        "y": 0,
        "z": 0
      },
      "contentRect": {
        "x": 0,
        "y": 0,
        "width": 300,
        "height": 600
      },
      "scale": 0.7
    },
    "9c72bc13-921d-45bd-bb66-60a0c517a620": {
      "position": {
        "x": 750,
        "y": 1500,
        "z": 5000
      },
      "rotation": {
        "x": 0,
        "y": 0,
        "z": 0,
        "w": 1
      },
      "viewCenter": {
        "x": 0,
        "y": 0,
        "z": 0
      },
      "contentRect": {
        "x": 0,
        "y": 0,
        "width": 300,
        "height": 600
      },
      "scale": 0.7
    },
    "179c3727-d8a6-486f-9c15-1db9ebad1c22": {
      "position": {
        "x": 750,
        "y": 1500,
        "z": 5000
      },
      "rotation": {
        "x": 0,
        "y": 0,
        "z": 0,
        "w": 1
      },
      "viewCenter": {
        "x": 0,
        "y": 0,
        "z": 0
      },
      "contentRect": {
        "x": 0,
        "y": 0,
        "width": 300,
        "height": 600
      },
      "scale": 0.7
    },
    "a1c882ad-4879-4538-a3d1-078f0b43e02f": {
      "position": {
        "x": 750,
        "y": 1500,
        "z": 5000
      },
      "rotation": {
        "x": 0,
        "y": 0,
        "z": 0,
        "w": 1
      },
      "viewCenter": {
        "x": 0,
        "y": 0,
        "z": 0
      },
      "contentRect": {
        "x": 0,
        "y": 0,
        "width": 300,
        "height": 600
      },
      "scale": 0.7
    },
    "741f65c5-9c57-4e87-b758-05d3f35ad98a": {
      "position": {
        "x": 750,
        "y": 1500,
        "z": 5000
      },
      "rotation": {
        "x": 0,
        "y": 0,
        "z": 0,
        "w": 1
      },
      "viewCenter": {
        "x": 0,
        "y": 0,
        "z": 0
      },
      "contentRect": {
        "x": 221.99999999999997,
        "y": 0,
        "width": 745,
        "height": 602
      },
      "scale": 0.7
    },
    "4c8ebd32-8b89-42e9-b4dd-3f4a624de838": {
      "position": {
        "x": 750,
        "y": 1500,
        "z": 5000
      },
      "rotation": {
        "x": 0,
        "y": 0,
        "z": 0,
        "w": 1
      },
      "viewCenter": {
        "x": 0,
        "y": 0,
        "z": 0
      },
      "contentRect": {
        "x": 0,
        "y": 0,
        "width": 300,
        "height": 600
      },
      "scale": 0.7
    },
    "f88a017a-eeb3-499b-9e24-67b1287f3f8c": {
      "position": {
        "x": 750,
        "y": 1500,
        "z": 5000
      },
      "rotation": {
        "x": 0,
        "y": 0,
        "z": 0,
        "w": 1
      },
      "viewCenter": {
        "x": 0,
        "y": 0,
        "z": 0
      },
      "contentRect": {
        "x": 0,
        "y": 0,
        "width": 300,
        "height": 600
      },
      "scale": 0.7
    },
    "edc64ed6-cf18-4ecb-92eb-429c4825dead": {
      "position": {
        "x": 750,
        "y": 1500,
        "z": 5000
      },
      "rotation": {
        "x": 0,
        "y": 0,
        "z": 0,
        "w": 1
      },
      "viewCenter": {
        "x": 0,
        "y": 0,
        "z": 0
      },
      "contentRect": {
        "x": 0,
        "y": 0,
        "width": 300,
        "height": 600
      },
      "scale": 0.7
    },
    "878746bf-2eb9-4d55-ae77-210c9638532e": {
      "position": {
        "x": 750,
        "y": 1500,
        "z": 5000
      },
      "rotation": {
        "x": 0,
        "y": 0,
        "z": 0,
        "w": 1
      },
      "viewCenter": {
        "x": 0,
        "y": 0,
        "z": 0
      },
      "contentRect": {
        "x": 0,
        "y": 0,
        "width": 300,
        "height": 600
      },
      "scale": 0.7
    },
    "7a9ef65d-40c5-4ded-a108-257392562e7e": {
      "position": {
        "x": 750,
        "y": 1500,
        "z": 5000
      },
      "rotation": {
        "x": 0,
        "y": 0,
        "z": 0,
        "w": 1
      },
      "viewCenter": {
        "x": 0,
        "y": 0,
        "z": 0
      },
      "contentRect": {
        "x": 0,
        "y": 0,
        "width": 300,
        "height": 600
      },
      "scale": 0.7
    },
    "abedf6fe-e7e1-4655-ade3-492586ca435b": {
      "position": {
        "x": 750,
        "y": 1500,
        "z": 5000
      },
      "rotation": {
        "x": 0,
        "y": 0,
        "z": 0,
        "w": 1
      },
      "viewCenter": {
        "x": 0,
        "y": 0,
        "z": 0
      },
      "contentRect": {
        "x": 0,
        "y": 0,
        "width": 300,
        "height": 600
      },
      "scale": 0.7
    },
    "534707f6-ee0a-468a-9c7e-3c311c11a095": {
      "position": {
        "x": 750,
        "y": 1500,
        "z": 5000
      },
      "rotation": {
        "x": 0,
        "y": 0,
        "z": 0,
        "w": 1
      },
      "viewCenter": {
        "x": 0,
        "y": 0,
        "z": 0
      },
      "contentRect": {
        "x": 0,
        "y": 0,
        "width": 300,
        "height": 600
      },
      "scale": 0.7
    },
    "a1025475-ec1b-4634-baec-4e9a2bbc4d93": {
      "position": {
        "x": 750,
        "y": 1500,
        "z": 5000
      },
      "rotation": {
        "x": 0,
        "y": 0,
        "z": 0,
        "w": 1
      },
      "viewCenter": {
        "x": 0,
        "y": 0,
        "z": 0
      },
      "contentRect": {
        "x": 221.99999999999997,
        "y": 0,
        "width": 745,
        "height": 602
      },
      "scale": 0.7
    },
    "065f81f5-ff26-4927-83d6-713b6b540fe2": {
      "position": {
        "x": 750,
        "y": 1500,
        "z": 5000
      },
      "rotation": {
        "x": 0,
        "y": 0,
        "z": 0,
        "w": 1
      },
      "viewCenter": {
        "x": 0,
        "y": 0,
        "z": 0
      },
      "contentRect": {
        "x": 0,
        "y": 0,
        "width": 300,
        "height": 600
      },
      "scale": 0.7
    },
    "7d955a14-b375-4637-bec8-90ff556bcf65": {
      "position": {
        "x": 750,
        "y": 1500,
        "z": 5000
      },
      "rotation": {
        "x": 0,
        "y": 0,
        "z": 0,
        "w": 1
      },
      "viewCenter": {
        "x": 0,
        "y": 0,
        "z": 0
      },
      "contentRect": {
        "x": 0,
        "y": 0,
        "width": 300,
        "height": 600
      },
      "scale": 0.7
    },
    "0a80b06e-77f1-40dd-804c-b04994751145": {
      "position": {
        "x": 750,
        "y": 1500,
        "z": 5000
      },
      "rotation": {
        "x": 0,
        "y": 0,
        "z": 0,
        "w": 1
      },
      "viewCenter": {
        "x": 0,
        "y": 0,
        "z": 0
      },
      "contentRect": {
        "x": 0,
        "y": 0,
        "width": 300,
        "height": 600
      },
      "scale": 0.7
    },
    "383832a0-8997-48a5-af8b-81d9655848d7": {
      "position": {
        "x": 750,
        "y": 1500,
        "z": 5000
      },
      "rotation": {
        "x": 0,
        "y": 0,
        "z": 0,
        "w": 1
      },
      "viewCenter": {
        "x": 0,
        "y": 0,
        "z": 0
      },
      "contentRect": {
        "x": 0,
        "y": 0,
        "width": 300,
        "height": 600
      },
      "scale": 0.7
    },
    "3b5b02c1-b039-4055-b49d-718742c9de60": {
      "position": {
        "x": 750,
        "y": 1500,
        "z": 5000
      },
      "rotation": {
        "x": 0,
        "y": 0,
        "z": 0,
        "w": 1
      },
      "viewCenter": {
        "x": 0,
        "y": 0,
        "z": 0
      },
      "contentRect": {
        "x": 0,
        "y": 0,
        "width": 300,
        "height": 600
      },
      "scale": 0.7
    },
    "c1b92f75-34b2-4811-994c-42133d2dea34": {
      "position": {
        "x": 750,
        "y": 1500,
        "z": 5000
      },
      "rotation": {
        "x": 0,
        "y": 0,
        "z": 0,
        "w": 1
      },
      "viewCenter": {
        "x": 0,
        "y": 0,
        "z": 0
      },
      "contentRect": {
        "x": 0,
        "y": 0,
        "width": 300,
        "height": 600
      },
      "scale": 0.7
    },
    "b02b2c71-7d07-405c-a4d4-aa257319dfe4": {
      "position": {
        "x": 750,
        "y": 1500,
        "z": 5000
      },
      "rotation": {
        "x": 0,
        "y": 0,
        "z": 0,
        "w": 1
      },
      "viewCenter": {
        "x": 0,
        "y": 0,
        "z": 0
      },
      "contentRect": {
        "x": 0,
        "y": 0,
        "width": 300,
        "height": 600
      },
      "scale": 0.7
    },
    "71235a7f-f29c-4a9a-9fe5-41fdac746f6b": {
      "position": {
        "x": 750,
        "y": 1500,
        "z": 5000
      },
      "rotation": {
        "x": 0,
        "y": 0,
        "z": 0,
        "w": 1
      },
      "viewCenter": {
        "x": 0,
        "y": 0,
        "z": 0
      },
      "contentRect": {
        "x": 0,
        "y": 0,
        "width": 300,
        "height": 600
      },
      "scale": 0.7
    },
    "c549ea75-cd19-468d-b872-31916812f6da": {
      "position": {
        "x": 750,
        "y": 1500,
        "z": 5000
      },
      "rotation": {
        "x": 0,
        "y": 0,
        "z": 0,
        "w": 1
      },
      "viewCenter": {
        "x": 0,
        "y": 0,
        "z": 0
      },
      "contentRect": {
        "x": 0,
        "y": 0,
        "width": 300,
        "height": 600
      },
      "scale": 0.7
    },
    "1495289b-28a1-4ff5-aeac-39dd33258ad1": {
      "position": {
        "x": 750,
        "y": 1500,
        "z": 5000
      },
      "rotation": {
        "x": 0,
        "y": 0,
        "z": 0,
        "w": 1
      },
      "viewCenter": {
        "x": 0,
        "y": 0,
        "z": 0
      },
      "contentRect": {
        "x": 0,
        "y": 0,
        "width": 300,
        "height": 600
      },
      "scale": 0.7
    },
    "e8b7b944-521f-441c-be7f-b713685708f6": {
      "position": {
        "x": 750,
        "y": 1500,
        "z": 5000
      },
      "rotation": {
        "x": 0,
        "y": 0,
        "z": 0,
        "w": 1
      },
      "viewCenter": {
        "x": 0,
        "y": 0,
        "z": 0
      },
      "contentRect": {
        "x": 0,
        "y": 0,
        "width": 300,
        "height": 600
      },
      "scale": 0.7
    },
    "411f554b-a709-4e2f-910f-035c1f9a746f": {
      "position": {
        "x": 750,
        "y": 1500,
        "z": 5000
      },
      "rotation": {
        "x": 0,
        "y": 0,
        "z": 0,
        "w": 1
      },
      "viewCenter": {
        "x": 0,
        "y": 0,
        "z": 0
      },
      "contentRect": {
        "x": 0,
        "y": 0,
        "width": 300,
        "height": 600
      },
      "scale": 0.7
    },
    "4fac56aa-f9a3-442e-a05d-dfb98045fcdf": {
      "position": {
        "x": 750,
        "y": 1500,
        "z": 5000
      },
      "rotation": {
        "x": 0,
        "y": 0,
        "z": 0,
        "w": 1
      },
      "viewCenter": {
        "x": 0,
        "y": 0,
        "z": 0
      },
      "contentRect": {
        "x": 0,
        "y": 0,
        "width": 300,
        "height": 600
      },
      "scale": 0.7
    },
    "034fdd34-8eb5-41e9-a348-76af9e683f89": {
      "position": {
        "x": 750,
        "y": 1500,
        "z": 5000
      },
      "rotation": {
        "x": 0,
        "y": 0,
        "z": 0,
        "w": 1
      },
      "viewCenter": {
        "x": 0,
        "y": 0,
        "z": 0
      },
      "contentRect": {
        "x": 0,
        "y": 0,
        "width": 300,
        "height": 600
      },
      "scale": 0.7
    },
    "f6f04a23-ff9b-4193-bec9-086245ae1160": {
      "position": {
        "x": 750,
        "y": 1500,
        "z": 5000
      },
      "rotation": {
        "x": 0,
        "y": 0,
        "z": 0,
        "w": 1
      },
      "viewCenter": {
        "x": 0,
        "y": 0,
        "z": 0
      },
      "contentRect": {
        "x": 0,
        "y": 0,
        "width": 300,
        "height": 600
      },
      "scale": 0.7
    },
    "ef58e9cf-d76d-491f-b6db-fee46af92794": {
      "position": {
        "x": 372.50000000000006,
        "y": 301,
        "z": 5000
      },
      "rotation": {
        "x": 0,
        "y": 0,
        "z": 0,
        "w": 1
      },
      "viewCenter": {
        "x": 0,
        "y": 0,
        "z": 0
      },
      "contentRect": {
        "x": -159.64285714285714,
        "y": -129.00000000000003,
        "width": 300,
        "height": 600
      },
      "scale": 0.7
    }
  },
  "camera-uuids": [
    "b84b8381-b0d5-4bde-a44a-b846cc861561",
    "ee4dd54d-d571-48fd-b7b2-188e2cc5b1f6",
    "2d6df1b9-3994-4ef9-afa0-a28e99598b38",
    "8c8615ca-7b4e-43c1-b2cc-f72964472297",
    "37571cfd-8ab2-41d5-89a4-919bc2257e6f",
    "ccb39f74-662f-429e-8cda-db02366bf329",
    "54ce050a-2514-4bb4-b5ed-5e1744cf83b8",
    "2034b8c5-1146-458f-8ba5-25be772802d6",
    "13cc6695-c655-4495-9675-6a468b3eaa56",
    "075ef6fe-19e9-48a4-9888-94c9a96669d3",
    "fc2e5167-dc70-498f-9c79-e6dcb2f72269",
    "4a6628bc-5169-4414-9121-557593015fb1",
    "ffda4a59-2bbf-4520-8804-1ee2f0b6a7a8",
    "30610f8e-e61d-4828-8baa-b7cd2a3dcda2",
    "d69e9f1c-5a10-4af2-b2e1-f1791b9ce753",
    "d27bc379-4a6b-4e9b-beb2-4bf70f9b1127",
    "6be07cc3-fad6-4fd7-8f13-cc76de2fcc01",
    "82aa19b1-0fe6-44f9-b6b2-0179d5eec652",
    "3f5f3bd5-c82f-4d47-ac9f-7424735b4f41",
    "9dbe4a48-eef1-4ad7-8922-37dc4e113efc",
    "1c15e859-8b57-4952-b5e6-4b24288d4c2d",
    "0abd7c88-5b0f-4b95-a22d-f723f2d30f98",
    "9c72bc13-921d-45bd-bb66-60a0c517a620",
    "179c3727-d8a6-486f-9c15-1db9ebad1c22",
    "a1c882ad-4879-4538-a3d1-078f0b43e02f",
    "741f65c5-9c57-4e87-b758-05d3f35ad98a",
    "4c8ebd32-8b89-42e9-b4dd-3f4a624de838",
    "f88a017a-eeb3-499b-9e24-67b1287f3f8c",
    "edc64ed6-cf18-4ecb-92eb-429c4825dead",
    "878746bf-2eb9-4d55-ae77-210c9638532e",
    "7a9ef65d-40c5-4ded-a108-257392562e7e",
    "abedf6fe-e7e1-4655-ade3-492586ca435b",
    "534707f6-ee0a-468a-9c7e-3c311c11a095",
    "a1025475-ec1b-4634-baec-4e9a2bbc4d93",
    "065f81f5-ff26-4927-83d6-713b6b540fe2",
    "7d955a14-b375-4637-bec8-90ff556bcf65",
    "0a80b06e-77f1-40dd-804c-b04994751145",
    "383832a0-8997-48a5-af8b-81d9655848d7",
    "3b5b02c1-b039-4055-b49d-718742c9de60",
    "c1b92f75-34b2-4811-994c-42133d2dea34",
    "b02b2c71-7d07-405c-a4d4-aa257319dfe4",
    "71235a7f-f29c-4a9a-9fe5-41fdac746f6b",
    "c549ea75-cd19-468d-b872-31916812f6da",
    "1495289b-28a1-4ff5-aeac-39dd33258ad1",
    "e8b7b944-521f-441c-be7f-b713685708f6",
    "411f554b-a709-4e2f-910f-035c1f9a746f",
    "4fac56aa-f9a3-442e-a05d-dfb98045fcdf",
    "034fdd34-8eb5-41e9-a348-76af9e683f89",
    "f6f04a23-ff9b-4193-bec9-086245ae1160",
    "ef58e9cf-d76d-491f-b6db-fee46af92794"
  ],
  "camera": {
    "color": [
      48,
      48,
      48,
      255
    ],
    "fov": 45,
    "far": 10000,
    "near": 0.01,
    "wheelSpeed": 0.01,
    "wanderSpeed": 35.15,
    "enableAcceleration": true,
    "size": "__default_design__",
    "far2D": 10000,
    "near2D": 1,
    "wheelSpeed2D": 6,
    "iso": 0,
    "aperture": 19,
    "shutter": 7
  },
  "scene_view": {
    "isSceneLightOn": true,
    "output_device": "__default_design__"
  },
  "game-view": {
    "scaleValue": 20,
    "sliderValue": 6,
    "fullScreen": false,
    "stats": false,
    "devicesInfo": {
      "name": "i18n:scene.game_view.design_resolution",
      "type": "design",
      "width": 1050,
      "height": 2100
    }
  }
}
